{"cameraMode":{"drawMode":0,"name":"Shaded","section":"Shading Mode"},"sceneLighting":true,"audioPlay":false,"sceneViewState":{"m_AlwaysRefresh":false,"showFog":true,"showSkybox":true,"showFlares":true,"showImageEffects":true,"showParticleSystems":true,"showVisualEffectGraphs":true,"m_FxEnabled":true},"in2DMode":false,"pivot":{"x":194.45433044433595,"y":49.040000915527347,"z":224.35321044921876},"rotation":{"x":0.3726818859577179,"y":-0.20133301615715028,"z":0.08318235725164414,"w":0.9020317792892456},"size":17.953092575073243,"orthographic":false}